schul_cloud_url_crawler/__init__.py
schul_cloud_url_crawler/__main__.py
schul_cloud_url_crawler/cli.py
schul_cloud_url_crawler/crawled_resource.py
schul_cloud_url_crawler/fetch.py
schul_cloud_url_crawler/resource_client.py
schul_cloud_url_crawler/tests/__init__.py
schul_cloud_url_crawler/tests/conftest.py
schul_cloud_url_crawler/tests/test_client_with_server.py
schul_cloud_url_crawler/tests/test_command_line_interface.py
schul_cloud_url_crawler/tests/test_crawled_resource.py
schul_cloud_url_crawler/tests/test_fetch_ressources.py
schul_cloud_url_crawler/tests/test_resource_client.py
schul_cloud_url_crawler/tests/test_tests.py
schul_cloud_url_crawler-1.0.17.dist-info/DESCRIPTION.rst
schul_cloud_url_crawler-1.0.17.dist-info/METADATA
schul_cloud_url_crawler-1.0.17.dist-info/RECORD
schul_cloud_url_crawler-1.0.17.dist-info/WHEEL
schul_cloud_url_crawler-1.0.17.dist-info/entry_points.txt
schul_cloud_url_crawler-1.0.17.dist-info/metadata.json
schul_cloud_url_crawler-1.0.17.dist-info/top_level.txt
