Metadata-Version: 2.0
Name: schul-cloud-url-crawler
Version: 1.0.17
Summary: Crawler for Schul-Cloud Ressources
Home-page: https://github.com/schul-cloud/url-crawler
Author: UNKNOWN
Author-email: UNKNOWN
License: UNKNOWN
Keywords: Schul-Cloud Content API,Crawler
Platform: UNKNOWN
Requires-Dist: certifi (==2017.4.17)
Requires-Dist: click (==6.7)
Requires-Dist: jsonschema (==2.6.0)
Requires-Dist: python-dateutil (==2.6.0)
Requires-Dist: requests (==2.13.0)
Requires-Dist: schul-cloud-resources-api-v1 (==1.0.0.80)
Requires-Dist: six (==1.10.0)
Requires-Dist: urllib3 (==1.21)
